dash_io/__init__.py
dash_io-0.0.2.dist-info/METADATA
dash_io-0.0.2.dist-info/WHEEL
dash_io-0.0.2.dist-info/top_level.txt
dash_io-0.0.2.dist-info/RECORD
