Metadata-Version: 2.1
Name: dash-io
Version: 0.0.2
Summary: An API prototype for simplifying IO in Dash
Home-page: https://github.com/plotly/dash-io
Author: Plotly
Author-email: xinghan@plot.ly
License: UNKNOWN
Platform: UNKNOWN
Classifier: Programming Language :: Python :: 3
Classifier: Operating System :: OS Independent
Requires-Python: >=3.6
Requires-Dist: Pillow (>=8.2)
Requires-Dist: pyarrow
Requires-Dist: pandas ; python_version < "3.7"
Requires-Dist: pandas (>=1.2) ; python_version >= "3.7"
